{
  "posts": [
    {
      "id": 1,
      "title": "json-server",
      "author": "typicode"
    }
  ],
  "Bankaccount": [
    {
      "AccountNo": "123456789879",
      "Name": "darpan parmar",
      "Email": "darpan6777@gmail.com",
      "PhoneNo": "9687177725",
      "BankName": "icicibank",
      "Gender": "male",
      "Address": "valsad",
      "Amount": "700000"
    },
    {
      "AccountNo": "123456789879",
      "Name": "darpan parmar",
      "Email": "darpan6777@gmail.com",
      "PhoneNo": "9687177725",
      "BankName": "icicibank",
      "Gender": "male",
      "Address": "valsad",
      "Amount": "700000"
    },
    {
      "AccountNo": "123456789879",
      "Name": "darpan parmar",
      "Email": "darpan6777@gmail.com",
      "PhoneNo": "9687177725",
      "BankName": "icicibank",
      "Gender": "male",
      "Address": "valsad",
      "Amount": "700000"
    },
    {
      "AccountNo": "123456789879",
      "Name": "darpan parmar",
      "Email": "darpan6777@gmail.com",
      "PhoneNo": "9687177725",
      "BankName": "icicibank",
      "Gender": "male",
      "Address": "valsad",
      "Amount": "700000"
    },
    {
      "AccountNo": "123456789879",
      "Name": "darpan parmar",
      "Email": "darpan6777@gmail.com",
      "PhoneNo": "9687177725",
      "BankName": "icicibank",
      "Gender": "male",
      "Address": "valsad",
      "Amount": "700000"
    }
  ],
  "profile": {
    "name": "typicode"
  }
}